modulbank/__init__.py
modulbank/client.py
modulbank/client_bank_exchange.py
modulbank/exceptions.py
modulbank/structs.py
modulbank/version.py
modulbank-0.0.9.dist-info/DESCRIPTION.rst
modulbank-0.0.9.dist-info/METADATA
modulbank-0.0.9.dist-info/RECORD
modulbank-0.0.9.dist-info/WHEEL
modulbank-0.0.9.dist-info/metadata.json
modulbank-0.0.9.dist-info/top_level.txt
