Metadata-Version: 2.0
Name: modulbank
Version: 0.0.9
Summary: Python client for ModulBank REST API
Home-page: https://github.com/otetz/modulbank
Author: Alexey Shevchenko
Author-email: otetz@me.com
License: MIT
Keywords: modulbank bank
Platform: UNKNOWN
Classifier: Intended Audience :: Developers
Classifier: Intended Audience :: Financial and Insurance Industry
Classifier: Intended Audience :: Information Technology
Classifier: Topic :: Office/Business :: Financial
Classifier: Topic :: Software Development :: Libraries
Classifier: License :: OSI Approved :: MIT License
Classifier: Programming Language :: Python
Classifier: Programming Language :: Python :: 3
Classifier: Programming Language :: Python :: 3.4
Classifier: Programming Language :: Python :: 3.5
Classifier: Programming Language :: Python :: 3.6
Requires-Dist: pytz
Requires-Dist: requests
